datalayer_core/__init__.py
datalayer_core/__main__.py
datalayer_core/__version__.py
datalayer_core/_version.py
datalayer_core/_pydoc/__init__.py
datalayer_core/_pydoc/replace_processor.py
datalayer_core/_pydoc/replace_renderer.py
datalayer_core/assets/about.md
datalayer_core/authn/__init__.py
datalayer_core/authn/authn.py
datalayer_core/authn/storage.py
datalayer_core/authn/strategies.py
datalayer_core/authn/server/__init__.py
datalayer_core/authn/server/__main__.py
datalayer_core/authn/server/http_server.py
datalayer_core/authn/server/keys.py
datalayer_core/authn/server/pages.py
datalayer_core/authn/server/state.py
datalayer_core/base/__init__.py
datalayer_core/base/application.py
datalayer_core/base/config.py
datalayer_core/base/migrate.py
datalayer_core/base/paths.py
datalayer_core/base/serverapplication.py
datalayer_core/base/troubleshoot.py
datalayer_core/cli/__init__.py
datalayer_core/cli/__main__.py
datalayer_core/cli/commands/README.md
datalayer_core/cli/commands/__init__.py
datalayer_core/cli/commands/about.py
datalayer_core/cli/commands/authn.py
datalayer_core/cli/commands/benchmarks.py
datalayer_core/cli/commands/console.py
datalayer_core/cli/commands/envs.py
datalayer_core/cli/commands/exec.py
datalayer_core/cli/commands/runtime_snapshots.py
datalayer_core/cli/commands/runtimes.py
datalayer_core/cli/commands/secrets.py
datalayer_core/cli/commands/tokens.py
datalayer_core/cli/commands/usage.py
datalayer_core/cli/commands/users.py
datalayer_core/cli/commands/web.py
datalayer_core/client/__init__.py
datalayer_core/client/client.py
datalayer_core/console/__init__.py
datalayer_core/console/consoleapp.py
datalayer_core/console/manager.py
datalayer_core/decorators/__init__.py
datalayer_core/decorators/datalayer.py
datalayer_core/displays/__init__.py
datalayer_core/displays/environments.py
datalayer_core/displays/me.py
datalayer_core/displays/runtime_snapshots.py
datalayer_core/displays/runtimes.py
datalayer_core/displays/secrets.py
datalayer_core-1.1.15.dist-info/METADATA
datalayer_core-1.1.15.dist-info/WHEEL
datalayer_core-1.1.15.dist-info/entry_points.txt
datalayer_core-1.1.15.dist-info/licenses/LICENSE
datalayer_core-1.1.15.dist-info/RECORD
