Metadata-Version: 2.1
Name: datalayer_core
Version: 1.1.15
Summary: Datalayer Core
Project-URL: Homepage, https://github.com/datalayer/core
Project-URL: Documentation, https://core.datalayer.tech
Project-URL: Repository, https://github.com/datalayer/core
Project-URL: Issues, https://github.com/datalayer/core/issues
Project-URL: Changelog, https://github.com/datalayer/core/blob/main/CHANGELOG.md
License: BSD-3-Clause
License-File: LICENSE
Classifier: Framework :: Jupyter
Classifier: Intended Audience :: Developers
Classifier: Intended Audience :: Science/Research
Classifier: Intended Audience :: System Administrators
Classifier: Programming Language :: Python
Classifier: Programming Language :: Python :: 3
Classifier: Programming Language :: Python :: 3.10
Classifier: Programming Language :: Python :: 3.11
Classifier: Programming Language :: Python :: 3.12
Classifier: Programming Language :: Python :: 3.13
Requires-Python: >=3.10
Requires-Dist: jupyter-console
Requires-Dist: jupyter-kernel-client
Requires-Dist: jupyter-nbmodel-client
Requires-Dist: jupyter-server<3,>=2.10
Requires-Dist: keyring==23.0.1
Requires-Dist: mcp
Requires-Dist: pydantic-settings
Requires-Dist: pydantic[email]
Requires-Dist: pyyaml>=6.0
Requires-Dist: questionary
Requires-Dist: requests
Requires-Dist: rich
Requires-Dist: traitlets
Requires-Dist: typer
Provides-Extra: docs
Requires-Dist: click>=8.3.1; extra == 'docs'
Requires-Dist: npdoc-to-md; extra == 'docs'
Requires-Dist: pydoc-markdown>=4.0; extra == 'docs'
Provides-Extra: examples
Requires-Dist: fastapi; extra == 'examples'
Requires-Dist: pydantic; extra == 'examples'
Requires-Dist: scikit-learn; extra == 'examples'
Requires-Dist: streamlit; extra == 'examples'
Requires-Dist: torch; extra == 'examples'
Requires-Dist: uvicorn; extra == 'examples'
Provides-Extra: test
Requires-Dist: coverage; extra == 'test'
Requires-Dist: mypy; extra == 'test'
Requires-Dist: pytest; extra == 'test'
Requires-Dist: pytest-asyncio; extra == 'test'
Requires-Dist: pytest-cov; extra == 'test'
Requires-Dist: pytest-jupyter; extra == 'test'
Requires-Dist: pytest-tornasync; extra == 'test'
Requires-Dist: python-dotenv; extra == 'test'
Requires-Dist: types-requests; extra == 'test'
Requires-Dist: typing-extensions; extra == 'test'
